README.md
setup.py
hsmwiz/ActionChangePIN.py
hsmwiz/ActionCheckEngine.py
hsmwiz/ActionExplore.py
hsmwiz/ActionFormat.py
hsmwiz/ActionGenCSR.py
hsmwiz/ActionGetPublicKey.py
hsmwiz/ActionIdentify.py
hsmwiz/ActionInit.py
hsmwiz/ActionKeyGen.py
hsmwiz/ActionPutCRT.py
hsmwiz/ActionRemoveKey.py
hsmwiz/ActionUnblock.py
hsmwiz/ActionVerifyPIN.py
hsmwiz/BaseAction.py
hsmwiz/CmdTools.py
hsmwiz/FriendlyArgumentParser.py
hsmwiz/HardwareSecurityModule.py
hsmwiz/MultiCommand.py
hsmwiz/PrefixMatcher.py
hsmwiz/__init__.py
hsmwiz/__main__.py
hsmwiz.egg-info/PKG-INFO
hsmwiz.egg-info/SOURCES.txt
hsmwiz.egg-info/dependency_links.txt
hsmwiz.egg-info/entry_points.txt
hsmwiz.egg-info/top_level.txt