Metadata-Version: 2.1
Name: hsmwiz
Version: 0.0.2
Summary: Frontend for OpenSC, pkcs11tool and pkcs15tool to ease handling of HSM smartcards
Home-page: https://github.com/johndoe31415/hsmwiz
Author: Johannes Bauer
Author-email: joe@johannes-bauer.com
License: gpl-3.0
Download-URL: https://github.com/johndoe31415/hsmwiz/archive/0.0.2.tar.gz
Keywords: hsm,pcsc,smart,card,frontend,openssl
Platform: UNKNOWN
Classifier: Development Status :: 5 - Production/Stable
Classifier: Intended Audience :: Developers
Classifier: License :: OSI Approved :: GNU General Public License v3 (GPLv3)
Classifier: Programming Language :: Python :: 3
Classifier: Programming Language :: Python :: 3 :: Only
Classifier: Programming Language :: Python :: 3.5
Classifier: Programming Language :: Python :: 3.6
Classifier: Programming Language :: Python :: 3.7
Classifier: Programming Language :: Python :: 3.8
